squice/BinaryFile.py
squice/DataLoaders.py
squice/GridMaker.py
squice/Matrix3d.py
squice/ModulePredict.py
squice/MtxDisplay.py
squice/MtxInterpolator.py
squice/SpaceTransform.py
squice/VectorThree.py
squice/__init__.py
tests/__init__.py
tests/speed/__init__.py
tests/speed/help_speed.py
tests/speed/test_dataloaders.py
tests/utility/__init__.py
tests/utility/test_grid.py
tests/utility/test_loader.py
tests/utility/test_slice.py
squice-0.6.dist-info/LICENSE
squice-0.6.dist-info/METADATA
squice-0.6.dist-info/WHEEL
squice-0.6.dist-info/top_level.txt
squice-0.6.dist-info/RECORD
